baseemoji/__init__.py
baseemoji/__main__.py
baseemoji/_version.py
base_emoji-0.0.3.dist-info/LICENSE
base_emoji-0.0.3.dist-info/METADATA
base_emoji-0.0.3.dist-info/WHEEL
base_emoji-0.0.3.dist-info/entry_points.txt
base_emoji-0.0.3.dist-info/top_level.txt
base_emoji-0.0.3.dist-info/RECORD
