Metadata-Version: 2.1
Name: base-emoji
Version: 0.0.3
Summary: A binary-to-emoji encoding scheme that representbinary data in a subset of the Unicode Emoji symbols.
Home-page: https://github.com/amoallim15/base-emoji
Author: Ali Moallim
Author-email: amoallim15@gmail.com
License: MIT
Keywords: base emoji encode decode scheme
Platform: UNKNOWN
Classifier: Environment :: Console
Classifier: Intended Audience :: Developers
Classifier: Operating System :: OS Independent
Classifier: Programming Language :: Python :: 3.5
Requires-Python: >= 3.5
